{
  "request": {
    "api_version": "xdebug.v1",
    "action": "session.open",
    "target": {
      "fsdb": "<xverif-repo>/xdebug/testdata/waveform/ai_complex_wave/out/waves.fsdb"
    },
    "args": {
      "name": "sample_wave"
    },
    "output": {
      "verbosity": "compact"
    }
  },
  "response": {
    "api_version": "xdebug.v1",
    "ok": true,
    "action": "session.open",
    "tool": {
      "name": "xdebug",
      "version": "0.1.0"
    },
    "session": {
      "id": "sample_wave",
      "session_id": "sample_wave",
      "mode": "waveform",
      "fsdb": "<xverif-repo>/xdebug/testdata/waveform/ai_complex_wave/out/waves.fsdb",
      "socket_path": "<repo>/tmp/xdebug_action_sampling/home/.xdebug/engine/sessions/sample_wave_98f4709ce8a8a5b3/socket",
      "transport": "uds",
      "file_dir": "<repo>/tmp/xdebug_action_sampling/home/.xdebug/engine/sessions/sample_wave_98f4709ce8a8a5b3/transport",
      "server_host": "localhost.localdomain"
    },
    "summary": {
      "session_id": "sample_wave",
      "mode": "waveform"
    },
    "data": {
      "session": {
        "id": "sample_wave",
        "session_id": "sample_wave",
        "mode": "waveform",
        "fsdb": "<xverif-repo>/xdebug/testdata/waveform/ai_complex_wave/out/waves.fsdb",
        "socket_path": "<repo>/tmp/xdebug_action_sampling/home/.xdebug/engine/sessions/sample_wave_98f4709ce8a8a5b3/socket",
        "transport": "uds",
        "file_dir": "<repo>/tmp/xdebug_action_sampling/home/.xdebug/engine/sessions/sample_wave_98f4709ce8a8a5b3/transport",
        "server_host": "localhost.localdomain"
      }
    },
    "findings": [],
    "suggested_next_actions": [],
    "warnings": [],
    "error": null,
    "meta": {
      "truncated": false
    }
  },
  "stderr": ""
}