{
  "$schema": "https://json-schema.org/draft/2020-12/schema",
  "$id": "xdebug.counter.statistics.request.v1",
  "title": "counter.statistics request",
  "type": "object",
  "required": [
    "api_version",
    "action",
    "target",
    "args"
  ],
  "properties": {
    "api_version": {
      "type": "string",
      "enum": [
        "xdebug.v1"
      ]
    },
    "request_id": {
      "type": "string"
    },
    "action": {
      "type": "string",
      "enum": [
        "counter.statistics"
      ]
    },
    "target": {
      "type": "object"
    },
    "args": {
      "type": "object",
      "required": [
        "clock",
        "time_range",
        "vld",
        "cnt"
      ],
      "properties": {
        "clock": {
          "type": "string",
          "description": "采样、统计或协议检查使用的 clock 信号路径。"
        },
        "sampling": {
          "type": "string",
          "enum": [
            "posedge",
            "negedge"
          ]
        },
        "time_range": {
          "type": "object",
          "description": "查询或分析的时间窗口。"
        },
        "vld": {
          "oneOf": [
            {
              "type": "string"
            },
            {
              "type": "object",
              "required": [
                "expr",
                "signals"
              ],
              "properties": {
                "expr": {
                  "type": "string"
                },
                "signals": {
                  "type": "object",
                  "additionalProperties": {
                    "type": "string"
                  }
                }
              },
              "additionalProperties": true
            }
          ],
          "description": "计数器统计使用的 valid 信号路径。"
        },
        "cnt": {
          "type": "string",
          "description": "计数器统计使用的 counter 信号路径。"
        },
        "max_samples": {
          "type": "integer"
        },
        "clk": {
          "type": "string"
        },
        "payload": {
          "type": "string"
        },
        "payloads": {
          "type": "array",
          "items": {
            "type": "string"
          }
        },
        "signal": {
          "type": "string"
        },
        "signals": {
          "oneOf": [
            {
              "type": "array",
              "items": {
                "type": "string"
              }
            },
            {
              "type": "object",
              "additionalProperties": {
                "type": "string"
              }
            }
          ]
        },
        "index": {
          "oneOf": [
            {
              "type": "integer"
            },
            {
              "type": "string"
            }
          ]
        },
        "begin": {
          "type": "string"
        },
        "end": {
          "type": "string"
        },
        "start": {
          "type": "string"
        },
        "kind": {
          "type": "string"
        },
        "output_file": {
          "type": "string"
        },
        "output_prefix": {
          "type": "string"
        },
        "max_events": {
          "type": "integer"
        },
        "max_findings": {
          "type": "integer"
        },
        "limit": {
          "type": "integer"
        },
        "rst_n": {
          "type": "string"
        },
        "edge": {
          "type": "string"
        },
        "format": {
          "type": "string"
        },
        "stream": {
          "type": "string"
        },
        "query": {
          "type": "object"
        },
        "streams": {
          "type": "array"
        },
        "config_path": {
          "type": "string"
        },
        "rc_path": {
          "type": "string"
        },
        "requested_time": {
          "type": "string"
        },
        "from_signal": {
          "type": "string"
        },
        "to_signal": {
          "type": "string"
        },
        "file": {
          "type": "string"
        },
        "line": {
          "type": "integer"
        },
        "expr": {
          "type": "string"
        },
        "scope": {
          "type": "string"
        },
        "name": {
          "type": "string"
        },
        "op": {
          "type": "string"
        },
        "conditions": {
          "type": "array",
          "items": {
            "type": "object"
          }
        },
        "time": {
          "type": "string"
        },
        "requests": {
          "type": "array",
          "items": {
            "type": "object"
          }
        },
        "session_id": {
          "type": "string"
        },
        "valid": {
          "type": "string"
        },
        "ready": {
          "type": "string"
        }
      },
      "additionalProperties": true
    },
    "limits": {
      "type": "object"
    },
    "output": {
      "type": "object"
    }
  },
  "additionalProperties": true,
  "description": "counter.statistics: 统计计数器行为。",
  "x-purpose": "统计计数器行为。",
  "x-how_it_works": "按 clock/vld/cnt 采样，分析递增、回绕、停顿和异常。",
  "x-when_to_use": "判断计数器是否符合预期。",
  "x-arg_contract_notes": "required: clock, time_range, vld, cnt"
}
